{
    "users": [
        {
            "id": 1677555000000,
            "email": "user@example.com",
            "password": "password123",
            "mobile": "9876543210",
            "fullName": "Test User"
        }
    ],
    "properties": [
        {
            "id": 1,
            "title": "Luxury Villa near Marina Beach",
            "location": "Marina Beach, Chennai",
            "type": "luxury",
            "price": 950,
            "beds": 3,
            "baths": 2,
            "ownerName": "Sabarishwaran",
            "ownerUpi": "sabar@upi",
            "image": "https://housing-images.n7net.in/01c16c28/3356845532aab845df7db08a755713ee/v0/medium/1_bhk_independent_house-for-rent-bolarum-Secunderabad-living_room.jpg",
            "rating": "4.8",
            "bookings": 85
        },
        {
            "id": 2,
            "title": "Modern Apartment in OMR",
            "location": "Navalur, OMR Road, Chennai",
            "type": "family",
            "price": 450,
            "beds": 2,
            "baths": 2,
            "ownerName": "Bhuvanesh",
            "ownerUpi": "bhuvan@upi",
            "image": "https://imganuncios.mitula.net/6_bhk_independent_house_in_neelankarai_for_rent_chennai_the_reference_number_is_19601644_9140000772096851637.jpg",
            "rating": "4.5",
            "bookings": 42
        },
        {
            "id": 3,
            "title": "Cozy Studio in Anna Nagar",
            "location": "Anna Nagar, Chennai",
            "type": "studio",
            "price": 250,
            "beds": 1,
            "baths": 1,
            "ownerName": "Revathi",
            "ownerUpi": "revathi@upi",
            "image": "https://img.staticmb.com/mbphoto/property/cropped_images/2025/Dec/06/Photo_h470_w1080/82371621_3_PropertyImage1764959600123_470_1080.jpg",
            "rating": "4.9",
            "bookings": 15
        },
        {
            "id": 4,
            "title": "Independent House in RS Puram",
            "location": "RS Puram, Coimbatore",
            "type": "luxury",
            "price": 1200,
            "beds": 3,
            "baths": 3,
            "ownerName": "Karthik S.",
            "ownerUpi": "karthik@upi",
            "image": "https://lscdn.blob.core.windows.net/property/rentalad//21_12_2025_14_03_06_IMG_20251121_WA0016.jpg",
            "rating": "4.9",
            "bookings": 60
        },
        {
            "id": 5,
            "title": "Affordable PG near PSG Tech",
            "location": "PSG Tech, Coimbatore",
            "type": "student",
            "price": 150,
            "beds": 1,
            "baths": 1,
            "ownerName": "Meera J.",
            "ownerUpi": "meera@upi",
            "image": "https://img.staticmb.com/mbphoto/property/cropped_images/2026/Jan/24/Photo_h470_w1080/83086021_1_WhatsApp-Image-2026-01-23-at-11-09-40-AM--1-_470_1080.jpeg",
            "rating": "4.3",
            "bookings": 120
        },
        {
            "id": 6,
            "title": "Premium Flat near Tidel Park",
            "location": "Peelamedu, Coimbatore",
            "type": "family",
            "price": 550,
            "beds": 2,
            "baths": 2,
            "ownerName": "Anjali R.",
            "ownerUpi": "anjali@upi",
            "image": "https://imagecdn.99acres.com/media1/35710/19/714219419M-1771314400145.webp",
            "rating": "4.7",
            "bookings": 45
        },
        {
            "id": 7,
            "title": "Traditional Home near Temple",
            "location": "Meenakshi Amman Temple, Madurai",
            "type": "family",
            "price": 350,
            "beds": 2,
            "baths": 1,
            "ownerName": "Vijay K.",
            "ownerUpi": "vijay@upi",
            "image": "https://peolands.com/wp-content/uploads/2024/06/1-25.jpg",
            "rating": "4.8",
            "bookings": 95
        },
        {
            "id": 8,
            "title": "Modern Bachelor Pad",
            "location": "Anna Nagar, Madurai",
            "type": "studio",
            "price": 200,
            "beds": 1,
            "baths": 1,
            "ownerName": "Ramesh P.",
            "ownerUpi": "ramesh@upi",
            "image": "https://imagecdn.99acres.com/media1/35316/1/706321843M-1769825965911.webp",
            "rating": "4.4",
            "bookings": 30
        },
        {
            "id": 9,
            "title": "Executive Flat near Textile Hub",
            "location": "Jawahar Bazaar, Karur",
            "type": "luxury",
            "price": 600,
            "beds": 2,
            "baths": 2,
            "ownerName": "Senthil M.",
            "ownerUpi": "senthil@upi",
            "image": "https://housing-images.n7net.in/01c16c28/3356845532aab845df7db08a755713ee/v0/medium/1_bhk_independent_house-for-rent-bolarum-Secunderabad-living_room.jpg",
            "rating": "4.6",
            "bookings": 25
        },
        {
            "id": 10,
            "title": "Simple House near Bus Stand",
            "location": "Bus Stand, Karur",
            "type": "family",
            "price": 300,
            "beds": 2,
            "baths": 1,
            "ownerName": "Mani G.",
            "ownerUpi": "mani@upi",
            "image": "https://imganuncios.mitula.net/6_bhk_independent_house_in_neelankarai_for_rent_chennai_the_reference_number_is_19601644_9140000772096851637.jpg",
            "rating": "4.2",
            "bookings": 18
        },
        {
            "id": 11,
            "title": "Heritage Stay near Rockfort",
            "location": "Rockfort, Trichy",
            "type": "luxury",
            "price": 800,
            "beds": 3,
            "baths": 2,
            "ownerName": "Arun M.",
            "ownerUpi": "arun@upi",
            "image": "https://img.staticmb.com/mbphoto/property/cropped_images/2025/Dec/06/Photo_h470_w1080/82371621_3_PropertyImage1764959600123_470_1080.jpg",
            "rating": "4.9",
            "bookings": 55
        },
        {
            "id": 12,
            "title": "Student Room near NIT Trichy",
            "location": "NIT Trichy, Trichy",
            "type": "student",
            "price": 100,
            "beds": 1,
            "baths": 1,
            "ownerName": "Baskar T.",
            "ownerUpi": "baskar@upi",
            "image": "https://lscdn.blob.core.windows.net/property/rentalad//21_12_2025_14_03_06_IMG_20251121_WA0016.jpg",
            "rating": "4.5",
            "bookings": 80
        },
        {
            "id": 13,
            "title": "Modern Villa in Yercaud Foothills",
            "location": "Yercaud Foot Hills, Salem",
            "type": "luxury",
            "price": 1500,
            "beds": 4,
            "baths": 3,
            "ownerName": "Selvam R.",
            "ownerUpi": "selvam@upi",
            "image": "https://img.staticmb.com/mbphoto/property/cropped_images/2026/Jan/24/Photo_h470_w1080/83086021_1_WhatsApp-Image-2026-01-23-at-11-09-40-AM--1-_470_1080.jpeg",
            "rating": "4.9",
            "bookings": 15
        },
        {
            "id": 14,
            "title": "Central Apartment Salem",
            "location": "New Bus Stand, Salem",
            "type": "family",
            "price": 400,
            "beds": 2,
            "baths": 2,
            "ownerName": "Kumar S.",
            "ownerUpi": "kumar@upi",
            "image": "https://imagecdn.99acres.com/media1/35710/19/714219419M-1771314400145.webp",
            "rating": "4.3",
            "bookings": 40
        },
        {
            "id": 15,
            "title": "Cotton City Guest House",
            "location": "Textile Market, Tiruppur",
            "type": "family",
            "price": 500,
            "beds": 3,
            "baths": 2,
            "ownerName": "Prakash L.",
            "ownerUpi": "prakash@upi",
            "image": "https://peolands.com/wp-content/uploads/2024/06/1-25.jpg",
            "rating": "4.6",
            "bookings": 22
        },
        {
            "id": 16,
            "title": "Industrialist Suite",
            "location": "Avinashi Road, Tiruppur",
            "type": "luxury",
            "price": 900,
            "beds": 2,
            "baths": 2,
            "ownerName": "Deepak V.",
            "ownerUpi": "deepak@upi",
            "image": "https://imagecdn.99acres.com/media1/35316/1/706321843M-1769825965911.webp",
            "rating": "4.8",
            "bookings": 12
        },
        {
            "id": 17,
            "title": "Mist View Cottage",
            "location": "Botanical Garden, Ooty",
            "type": "luxury",
            "price": 2000,
            "beds": 3,
            "baths": 3,
            "ownerName": "Rex A.",
            "ownerUpi": "rex@upi",
            "image": "https://housing-images.n7net.in/01c16c28/3356845532aab845df7db08a755713ee/v0/medium/1_bhk_independent_house-for-rent-bolarum-Secunderabad-living_room.jpg",
            "rating": "5.0",
            "bookings": 150
        },
        {
            "id": 18,
            "title": "Pine Hill Cabin",
            "location": "Observatory, Kodaikanal",
            "type": "luxury",
            "price": 1800,
            "beds": 2,
            "baths": 2,
            "ownerName": "Samy K.",
            "ownerUpi": "samy@upi",
            "image": "https://imganuncios.mitula.net/6_bhk_independent_house_in_neelankarai_for_rent_chennai_the_reference_number_is_19601644_9140000772096851637.jpg",
            "rating": "4.9",
            "bookings": 85
        },
        {
            "id": 19,
            "title": "Tea Estate Stay",
            "location": "Charing Cross, Ooty",
            "type": "family",
            "price": 1200,
            "beds": 2,
            "baths": 1,
            "ownerName": "Nithin B.",
            "ownerUpi": "nithin@upi",
            "image": "https://img.staticmb.com/mbphoto/property/cropped_images/2025/Dec/06/Photo_h470_w1080/82371621_3_PropertyImage1764959600123_470_1080.jpg",
            "rating": "4.7",
            "bookings": 65
        },
        {
            "id": 20,
            "title": "VIT Student Housing",
            "location": "VIT University, Vellore",
            "type": "student",
            "price": 200,
            "beds": 1,
            "baths": 1,
            "ownerName": "Lokesh M.",
            "ownerUpi": "lokesh@upi",
            "image": "https://lscdn.blob.core.windows.net/property/rentalad//21_12_2025_14_03_06_IMG_20251121_WA0016.jpg",
            "rating": "4.2",
            "bookings": 200
        },
        {
            "id": 21,
            "title": "Global Hospital Stay",
            "location": "CMC hospital, Vellore",
            "type": "family",
            "price": 600,
            "beds": 2,
            "baths": 2,
            "ownerName": "Ganesh R.",
            "ownerUpi": "ganesh@upi",
            "image": "https://img.staticmb.com/mbphoto/property/cropped_images/2026/Jan/24/Photo_h470_w1080/83086021_1_WhatsApp-Image-2026-01-23-at-11-09-40-AM--1-_470_1080.jpeg",
            "rating": "4.8",
            "bookings": 75
        },
        {
            "id": 22,
            "title": "River View Tirunelveli",
            "location": "Palayamkottai, Tirunelveli",
            "type": "family",
            "price": 350,
            "beds": 3,
            "baths": 2,
            "ownerName": "Sudhir P.",
            "ownerUpi": "sudhir@upi",
            "image": "https://imagecdn.99acres.com/media1/35710/19/714219419M-1771314400145.webp",
            "rating": "4.5",
            "bookings": 18
        },
        {
            "id": 23,
            "title": "Smart Flat in Erode",
            "location": "Perundurai Road, Erode",
            "type": "family",
            "price": 450,
            "beds": 2,
            "baths": 2,
            "ownerName": "Kathir V.",
            "ownerUpi": "kathir@upi",
            "image": "https://peolands.com/wp-content/uploads/2024/06/1-25.jpg",
            "rating": "4.6",
            "bookings": 28
        },
        {
            "id": 24,
            "title": "Temple City Suite",
            "location": "Big Temple, Thanjavur",
            "type": "luxury",
            "price": 750,
            "beds": 2,
            "baths": 2,
            "ownerName": "Moorthy S.",
            "ownerUpi": "moorthy@upi",
            "image": "https://imagecdn.99acres.com/media1/35316/1/706321843M-1769825965911.webp",
            "rating": "4.9",
            "bookings": 40
        }
    ],
    "bookings": []
}